inkeep_mcp_server/__main__.py
inkeep_mcp_server/app.py
inkeep_mcp_server/server.py
inkeep_mcp_server/settings.py
inkeep_mcp_server-0.1.1.dist-info/licenses/LICENSE
inkeep_mcp_server-0.1.1.dist-info/METADATA
inkeep_mcp_server-0.1.1.dist-info/WHEEL
inkeep_mcp_server-0.1.1.dist-info/entry_points.txt
inkeep_mcp_server-0.1.1.dist-info/top_level.txt
inkeep_mcp_server-0.1.1.dist-info/RECORD
